{
  "project_info": {
    "project_number": "960003392419",
    "project_id": "practica-1a5f2",
    "storage_bucket": "practica-1a5f2.firebasestorage.app"
  },
  "client": [
    {
      "client_info": {
        "mobilesdk_app_id": "1:960003392419:android:3a3db2b9bebbf664b0d016",
        "android_client_info": {
          "package_name": "com.elioco.loginappextra"
        }
      },
      "oauth_client": [],
      "api_key": [
        {
          "current_key": "AIzaSyD4zowqLeKUHfv_3sNS9kgr1ekuO9xmGIA"
        }
      ],
      "services": {
        "appinvite_service": {
          "other_platform_oauth_client": []
        }
      }
    }
  ],
  "configuration_version": "1"
}